pvp/__init__.py
pvp/main.py
pvp/alarm/__init__.py
pvp/alarm/alarm.py
pvp/alarm/alarm_manager.py
pvp/alarm/condition.py
pvp/alarm/rule.py
pvp/common/__init__.py
pvp/common/fashion.py
pvp/common/loggers.py
pvp/common/message.py
pvp/common/prefs.py
pvp/common/unit_conversion.py
pvp/common/utils.py
pvp/common/values.py
pvp/controller/__init__.py
pvp/controller/control_module.py
pvp/coordinator/__init__.py
pvp/coordinator/coordinator.py
pvp/coordinator/process_manager.py
pvp/coordinator/rpc.py
pvp/external/FiraCode-Bold.otf
pvp/external/FiraCode-Regular.otf
pvp/external/Fira_License.txt
pvp/external/PySide2-5.11.4a1-5.11.3-cp37-cp37m-linux_armv7l.whl
pvp/gui/__init__.py
pvp/gui/constraints.py
pvp/gui/main.py
pvp/gui/menus.py
pvp/gui/styles.py
pvp/gui/images/pvp_logo.png
pvp/gui/images/record.png
pvp/gui/widgets/__init__.py
pvp/gui/widgets/alarm_bar.py
pvp/gui/widgets/components.py
pvp/gui/widgets/control_panel.py
pvp/gui/widgets/dialog.py
pvp/gui/widgets/display.py
pvp/gui/widgets/plot.py
pvp/io/HALMock.py
pvp/io/__init__.py
pvp/io/hal.py
pvp/io/config/devices-old.ini
pvp/io/config/devices.ini
pvp/io/config/sim-devices.ini
pvp/io/devices/__init__.py
pvp/io/devices/base.py
pvp/io/devices/pins.py
pvp/io/devices/sensors.py
pvp/io/devices/valves.py
tests/__init__.py
tests/pigpio_mocks.py
tests/test_alarms.py
tests/test_common.py
tests/test_controller.py
tests/test_coordinator.py
tests/test_gui.py
tests/test_io_devices.py
tests/test_io_hal.py
tests/test_io_pins.py
tests/test_io_sensors.py
tests/test_io_valves.py
tests/test_logging.py
tests/test_main.py
tests/test_timeoutdecorator.py
tests/test_unit_conversion.py
pvp-0.3.0.dist-info/LICENSE
pvp-0.3.0.dist-info/METADATA
pvp-0.3.0.dist-info/WHEEL
pvp-0.3.0.dist-info/top_level.txt
pvp-0.3.0.dist-info/RECORD
